pycontrails-0.60.2.dist-info/RECORD
pycontrails-0.60.2.dist-info/WHEEL
pycontrails-0.60.2.dist-info/top_level.txt
pycontrails-0.60.2.dist-info/METADATA
pycontrails-0.60.2.dist-info/licenses/LICENSE
pycontrails-0.60.2.dist-info/licenses/NOTICE
pycontrails/_version.py
pycontrails/__init__.py
pycontrails/py.typed
pycontrails/core/vector.py
pycontrails/core/models.py
pycontrails/core/interpolation.py
pycontrails/core/fleet.py
pycontrails/core/flight.py
pycontrails/core/fuel.py
pycontrails/core/polygon.py
pycontrails/core/cache.py
pycontrails/core/__init__.py
pycontrails/core/rgi_cython.cpython-313-darwin.so
pycontrails/core/flightplan.py
pycontrails/core/met.py
pycontrails/core/aircraft_performance.py
pycontrails/core/airports.py
pycontrails/core/met_var.py
pycontrails/core/coordinates.py
pycontrails/datalib/goes.py
pycontrails/datalib/landsat.py
pycontrails/datalib/geo_utils.py
pycontrails/datalib/__init__.py
pycontrails/datalib/gruan.py
pycontrails/datalib/met_utils.py
pycontrails/datalib/sentinel.py
pycontrails/datalib/himawari/himawari.py
pycontrails/datalib/himawari/__init__.py
pycontrails/datalib/himawari/header_struct.py
pycontrails/datalib/_met_utils/metsource.py
pycontrails/datalib/ecmwf/arco_era5.py
pycontrails/datalib/ecmwf/era5.py
pycontrails/datalib/ecmwf/era5_model_level.py
pycontrails/datalib/ecmwf/hres.py
pycontrails/datalib/ecmwf/variables.py
pycontrails/datalib/ecmwf/hres_model_level.py
pycontrails/datalib/ecmwf/__init__.py
pycontrails/datalib/ecmwf/common.py
pycontrails/datalib/ecmwf/model_levels.py
pycontrails/datalib/ecmwf/ifs.py
pycontrails/datalib/ecmwf/static/model_level_dataframe_v20240418.csv
pycontrails/datalib/gfs/gfs.py
pycontrails/datalib/gfs/variables.py
pycontrails/datalib/gfs/__init__.py
pycontrails/datalib/spire/spire.py
pycontrails/datalib/spire/__init__.py
pycontrails/datalib/spire/exceptions.py
pycontrails/datalib/dwd/icon.py
pycontrails/datalib/dwd/__init__.py
pycontrails/datalib/dwd/ods.py
pycontrails/datalib/leo_utils/sentinel_metadata.py
pycontrails/datalib/leo_utils/landsat_metadata.py
pycontrails/datalib/leo_utils/__init__.py
pycontrails/datalib/leo_utils/vis.py
pycontrails/datalib/leo_utils/search.py
